dontpanic/__init__.py
dontpanic/dontpanic.py
dontpanic-0.1.0.dist-info/METADATA
dontpanic-0.1.0.dist-info/WHEEL
dontpanic-0.1.0.dist-info/top_level.txt
dontpanic-0.1.0.dist-info/RECORD
