Metadata-Version: 2.2
Name: dontpanic
Version: 0.1.0
Summary: Suppress Ctrl+C traceback spam.
Home-page: https://github.com/thunderpoot/dontpanic
Author: T E Vaughan
Author-email: T E Vaughan <underwood@underwood.network>
License: MIT
Project-URL: Homepage, https://github.com/thunderpoot/dontpanic
Project-URL: Repository, https://github.com/thunderpoot/dontpanic
Classifier: Development Status :: 4 - Beta
Classifier: Intended Audience :: Developers
Classifier: License :: OSI Approved :: MIT License
Classifier: Programming Language :: Python :: 3
Classifier: Topic :: Software Development :: Libraries
Classifier: Topic :: System :: Shells
Requires-Python: >=3.6
